{
    "DlBookmark": {
        "Version": 1,
        "Sections": [
            {
                "Section": "Project",
                "Bookmarks": [
                    {
                        "Bookmark": "flame setups",
                        "Path": "<project home>",
                        "Visibility": "Global"
                    },
                    {
                        "Bookmark": "PROJEKTS",
                        "Path": "/PROJEKTS/",
                        "Visibility": "Global"
                    },
                    {
                        "Bookmark": "projekt home",
                        "Path": "/PROJEKTS/241031_premiere_test_01/",
                        "Visibility": "Global"
                    },
                    {
                        "Folder": "projekt directories",
                        "Bookmarks": [
                            {
                                "Folder": "assets",
                                "Bookmarks": [
                                    {
                                        "Bookmark": "assets",
                                        "Path": "/PROJEKTS/241031_premiere_test_01/assets",
                                        "Visibility": "Global"
                                    },
                                    {
                                        "Bookmark": "artwork",
                                        "Path": "/PROJEKTS/241031_premiere_test_01/assets/artwork",
                                        "Visibility": "Global"
                                    },
                                    {
                                        "Bookmark": "audio",
                                        "Path": "/PROJEKTS/241031_premiere_test_01/assets/audio",
                                        "Visibility": "Global"
                                    },
                                    {
                                        "Bookmark": "dub",
                                        "Path": "/PROJEKTS/241031_premiere_test_01/assets/audio/dub",
                                        "Visibility": "Global"
                                    },
                                    {
                                        "Bookmark": "mix",
                                        "Path": "/PROJEKTS/241031_premiere_test_01/assets/audio/mix",
                                        "Visibility": "Global"
                                    },
                                    {
                                        "Bookmark": "music",
                                        "Path": "/PROJEKTS/241031_premiere_test_01/assets/audio/music",
                                        "Visibility": "Global"
                                    },
                                    {
                                        "Bookmark": "production",
                                        "Path": "/PROJEKTS/241031_premiere_test_01/assets/audio/production",
                                        "Visibility": "Global"
                                    },
                                    {
                                        "Bookmark": "sound_effects",
                                        "Path": "/PROJEKTS/241031_premiere_test_01/assets/audio/sound_effects",
                                        "Visibility": "Global"
                                    },
                                    {
                                        "Bookmark": "stems",
                                        "Path": "/PROJEKTS/241031_premiere_test_01/assets/audio/stems",
                                        "Visibility": "Global"
                                    },
                                    {
                                        "Bookmark": "voiceover",
                                        "Path": "/PROJEKTS/241031_premiere_test_01/assets/audio/voiceover",
                                        "Visibility": "Global"
                                    },
                                    {
                                        "Bookmark": "cgi",
                                        "Path": "/PROJEKTS/241031_premiere_test_01/assets/cgi",
                                        "Visibility": "Global"
                                    },
                                    {
                                        "Bookmark": "font",
                                        "Path": "/PROJEKTS/241031_premiere_test_01/assets/font",
                                        "Visibility": "Global"
                                    },
                                    {
                                        "Bookmark": "footage",
                                        "Path": "/PROJEKTS/241031_premiere_test_01/assets/footage",
                                        "Visibility": "Global"
                                    },
                                    {
                                        "Bookmark": "graded",
                                        "Path": "/PROJEKTS/241031_premiere_test_01/assets/footage/graded",
                                        "Visibility": "Global"
                                    },
                                    {
                                        "Bookmark": "raw",
                                        "Path": "/PROJEKTS/241031_premiere_test_01/assets/footage/raw",
                                        "Visibility": "Global"
                                    },
                                    {
                                        "Bookmark": "stock",
                                        "Path": "/PROJEKTS/241031_premiere_test_01/assets/footage/stock",
                                        "Visibility": "Global"
                                    },
                                    {
                                        "Bookmark": "transcodes",
                                        "Path": "/PROJEKTS/241031_premiere_test_01/assets/footage/transcodes",
                                        "Visibility": "Global"
                                    },
                                    {
                                        "Bookmark": "graphics",
                                        "Path": "/PROJEKTS/241031_premiere_test_01/assets/graphics",
                                        "Visibility": "Global"
                                    },
                                    {
                                        "Bookmark": "images",
                                        "Path": "/PROJEKTS/241031_premiere_test_01/assets/images",
                                        "Visibility": "Global"
                                    },
                                    {
                                        "Bookmark": "legal",
                                        "Path": "/PROJEKTS/241031_premiere_test_01/assets/legal",
                                        "Visibility": "Global"
                                    },
                                    {
                                        "Bookmark": "matchmoving",
                                        "Path": "/PROJEKTS/241031_premiere_test_01/assets/matchmoving",
                                        "Visibility": "Global"
                                    },
                                    {
                                        "Bookmark": "miscellaneous",
                                        "Path": "/PROJEKTS/241031_premiere_test_01/assets/miscellaneous",
                                        "Visibility": "Global"
                                    },
                                    {
                                        "Bookmark": "paint",
                                        "Path": "/PROJEKTS/241031_premiere_test_01/assets/paint",
                                        "Visibility": "Global"
                                    },
                                    {
                                        "Bookmark": "photoshop",
                                        "Path": "/PROJEKTS/241031_premiere_test_01/assets/photoshop",
                                        "Visibility": "Global"
                                    },
                                    {
                                        "Bookmark": "roto",
                                        "Path": "/PROJEKTS/241031_premiere_test_01/assets/roto",
                                        "Visibility": "Global"
                                    },
                                    {
                                        "Bookmark": "slates",
                                        "Path": "/PROJEKTS/241031_premiere_test_01/assets/slates",
                                        "Visibility": "Global"
                                    },
                                    {
                                        "Bookmark": "subtitles",
                                        "Path": "/PROJEKTS/241031_premiere_test_01/assets/subtitles",
                                        "Visibility": "Global"
                                    },
                                    {
                                        "Bookmark": "supers",
                                        "Path": "/PROJEKTS/241031_premiere_test_01/assets/supers",
                                        "Visibility": "Global"
                                    },
                                    {
                                        "Bookmark": "titles",
                                        "Path": "/PROJEKTS/241031_premiere_test_01/assets/titles",
                                        "Visibility": "Global"
                                    },
                                    {
                                        "Bookmark": "tracking",
                                        "Path": "/PROJEKTS/241031_premiere_test_01/assets/tracking",
                                        "Visibility": "Global"
                                    },
                                    {
                                        "Bookmark": "video",
                                        "Path": "/PROJEKTS/241031_premiere_test_01/assets/video",
                                        "Visibility": "Global"
                                    }
                                ]
                            },
                            {
                                "Folder": "editorial",
                                "Bookmarks": [
                                    {
                                        "Bookmark": "editorial",
                                        "Path": "/PROJEKTS/241031_premiere_test_01/editorial",
                                        "Visibility": "Global"
                                    },
                                    {
                                        "Bookmark": "aaf",
                                        "Path": "/PROJEKTS/241031_premiere_test_01/editorial/aaf",
                                        "Visibility": "Global"
                                    },
                                    {
                                        "Bookmark": "davinci_resolve",
                                        "Path": "/PROJEKTS/241031_premiere_test_01/editorial/davinci_resolve",
                                        "Visibility": "Global"
                                    },
                                    {
                                        "Bookmark": "edl",
                                        "Path": "/PROJEKTS/241031_premiere_test_01/editorial/edl",
                                        "Visibility": "Global"
                                    },
                                    {
                                        "Bookmark": "final_cut_pro",
                                        "Path": "/PROJEKTS/241031_premiere_test_01/editorial/final_cut_pro",
                                        "Visibility": "Global"
                                    },
                                    {
                                        "Bookmark": "premiere",
                                        "Path": "/PROJEKTS/241031_premiere_test_01/editorial/premiere",
                                        "Visibility": "Global"
                                    },
                                    {
                                        "Bookmark": "prep",
                                        "Path": "/PROJEKTS/241031_premiere_test_01/editorial/prep",
                                        "Visibility": "Global"
                                    },
                                    {
                                        "Bookmark": "xml",
                                        "Path": "/PROJEKTS/241031_premiere_test_01/editorial/xml",
                                        "Visibility": "Global"
                                    }
                                ]
                            },
                            {
                                "Folder": "flame",
                                "Bookmarks": [
                                    {
                                        "Bookmark": "flame",
                                        "Path": "/PROJEKTS/241031_premiere_test_01/flame",
                                        "Visibility": "Global"
                                    },
                                    {
                                        "Bookmark": "archives",
                                        "Path": "/PROJEKTS/241031_premiere_test_01/flame/archives",
                                        "Visibility": "Global"
                                    },
                                    {
                                        "Bookmark": "iterations",
                                        "Path": "/PROJEKTS/241031_premiere_test_01/flame/iterations",
                                        "Visibility": "Global"
                                    },
                                    {
                                        "Bookmark": "setups",
                                        "Path": "/PROJEKTS/241031_premiere_test_01/flame/setups",
                                        "Visibility": "Global"
                                    }
                                ]
                            },
                            {
                                "Folder": "masters",
                                "Bookmarks": [
                                    {
                                        "Bookmark": "masters",
                                        "Path": "/PROJEKTS/241031_premiere_test_01/masters",
                                        "Visibility": "Global"
                                    },
                                    {
                                        "Bookmark": "master_edits",
                                        "Path": "/PROJEKTS/241031_premiere_test_01/masters/master_edits",
                                        "Visibility": "Global"
                                    },
                                    {
                                        "Bookmark": "slated_masters",
                                        "Path": "/PROJEKTS/241031_premiere_test_01/masters/slated_masters",
                                        "Visibility": "Global"
                                    },
                                    {
                                        "Bookmark": "versioned_masters",
                                        "Path": "/PROJEKTS/241031_premiere_test_01/masters/versioned_masters",
                                        "Visibility": "Global"
                                    }
                                ]
                            },
                            {
                                "Folder": "reference",
                                "Bookmarks": [
                                    {
                                        "Bookmark": "reference",
                                        "Path": "/PROJEKTS/241031_premiere_test_01/reference",
                                        "Visibility": "Global"
                                    },
                                    {
                                        "Bookmark": "reference_images",
                                        "Path": "/PROJEKTS/241031_premiere_test_01/reference/reference_images",
                                        "Visibility": "Global"
                                    },
                                    {
                                        "Bookmark": "reference_movies",
                                        "Path": "/PROJEKTS/241031_premiere_test_01/reference/reference_movies",
                                        "Visibility": "Global"
                                    },
                                    {
                                        "Bookmark": "reference_style_guide",
                                        "Path": "/PROJEKTS/241031_premiere_test_01/reference/reference_style_guide",
                                        "Visibility": "Global"
                                    }
                                ]
                            },
                            {
                                "Folder": "scenes",
                                "Bookmarks": [
                                    {
                                        "Bookmark": "scenes",
                                        "Path": "/PROJEKTS/241031_premiere_test_01/scenes",
                                        "Visibility": "Global"
                                    },
                                    {
                                        "Bookmark": "3ds",
                                        "Path": "/PROJEKTS/241031_premiere_test_01/scenes/3ds",
                                        "Visibility": "Global"
                                    },
                                    {
                                        "Bookmark": "alembic",
                                        "Path": "/PROJEKTS/241031_premiere_test_01/scenes/alembic",
                                        "Visibility": "Global"
                                    },
                                    {
                                        "Bookmark": "baselight",
                                        "Path": "/PROJEKTS/241031_premiere_test_01/scenes/baselight",
                                        "Visibility": "Global"
                                    },
                                    {
                                        "Bookmark": "blender",
                                        "Path": "/PROJEKTS/241031_premiere_test_01/scenes/blender",
                                        "Visibility": "Global"
                                    },
                                    {
                                        "Bookmark": "c4d",
                                        "Path": "/PROJEKTS/241031_premiere_test_01/scenes/c4d",
                                        "Visibility": "Global"
                                    },
                                    {
                                        "Bookmark": "cut",
                                        "Path": "/PROJEKTS/241031_premiere_test_01/scenes/cut",
                                        "Visibility": "Global"
                                    },
                                    {
                                        "Bookmark": "fbx",
                                        "Path": "/PROJEKTS/241031_premiere_test_01/scenes/fbx",
                                        "Visibility": "Global"
                                    },
                                    {
                                        "Bookmark": "geometry",
                                        "Path": "/PROJEKTS/241031_premiere_test_01/scenes/geometry",
                                        "Visibility": "Global"
                                    },
                                    {
                                        "Bookmark": "houdini",
                                        "Path": "/PROJEKTS/241031_premiere_test_01/scenes/houdini",
                                        "Visibility": "Global"
                                    },
                                    {
                                        "Bookmark": "maya",
                                        "Path": "/PROJEKTS/241031_premiere_test_01/scenes/maya",
                                        "Visibility": "Global"
                                    },
                                    {
                                        "Bookmark": "resolve",
                                        "Path": "/PROJEKTS/241031_premiere_test_01/scenes/resolve",
                                        "Visibility": "Global"
                                    },
                                    {
                                        "Bookmark": "unity",
                                        "Path": "/PROJEKTS/241031_premiere_test_01/scenes/unity",
                                        "Visibility": "Global"
                                    },
                                    {
                                        "Bookmark": "unreal_engine",
                                        "Path": "/PROJEKTS/241031_premiere_test_01/scenes/unreal_engine",
                                        "Visibility": "Global"
                                    },
                                    {
                                        "Bookmark": "usd",
                                        "Path": "/PROJEKTS/241031_premiere_test_01/scenes/usd",
                                        "Visibility": "Global"
                                    }
                                ]
                            },
                            {
                                "Folder": "shots",
                                "Bookmarks": [
                                    {
                                        "Bookmark": "shots",
                                        "Path": "/PROJEKTS/241031_premiere_test_01/shots",
                                        "Visibility": "Global"
                                    }
                                ]
                            },
                            {
                                "Folder": "tmp",
                                "Bookmarks": [
                                    {
                                        "Bookmark": "tmp",
                                        "Path": "/PROJEKTS/241031_premiere_test_01/tmp",
                                        "Visibility": "Global"
                                    }
                                ]
                            },
                            {
                                "Folder": "utilities",
                                "Bookmarks": [
                                    {
                                        "Bookmark": "utilities",
                                        "Path": "/PROJEKTS/241031_premiere_test_01/utilities",
                                        "Visibility": "Global"
                                    },
                                    {
                                        "Bookmark": "flame_colortoolkit (linux)",
                                        "Path": "/opt/Autodesk/Synergy/SynColor/Shared/transforms/flame_colortoolkit",
                                        "Visibility": "Global"
                                    },
                                    {
                                        "Bookmark": "flame_colortoolkit (macos)",
                                        "Path": "/Applications/Autodesk/Synergy/SynColor/Shared/transforms/flame_colortoolkit",
                                        "Visibility": "Global"
                                    }
                                ]
                            },
                            {
                                "Folder": "version",
                                "Bookmarks": [
                                    {
                                        "Bookmark": "version",
                                        "Path": "/PROJEKTS/241031_premiere_test_01/version",
                                        "Visibility": "Global"
                                    }
                                ]
                            },
                            {
                                "Folder": "work_in_progress",
                                "Bookmarks": [
                                    {
                                        "Bookmark": "work_in_progress",
                                        "Path": "/PROJEKTS/241031_premiere_test_01/work_in_progress",
                                        "Visibility": "Global"
                                    },
                                    {
                                        "Bookmark": "postings",
                                        "Path": "/PROJEKTS/241031_premiere_test_01/work_in_progress/postings",
                                        "Visibility": "Global"
                                    }
                                ]
                            }
                        ]
                    }
                ]
            }
        ]
    }
}