{
    "group": "RED Camera Resolutions",
    "items": [
        {
            "separator": true,
            "separator_name": "+ ----------- RED 6.5K - Anamorphic -------------- +",
            "items": [
                {
                    "name": "6144 x 3456 | RED 6.5K 16:9 Ana 1.3x",
                    "width": 6144,
                    "height": 3456,
                    "storage_aspect_ratio": 2.311101,
                    "display_aspect_ratio": 2.311101,
                    "pixel_aspect_ratio": 1.0
                },
                {
                    "name": "6656 x 832 | RED 6.5K 8:1 Ana 1.3x",
                    "width": 6656,
                    "height": 832,
                    "storage_aspect_ratio": 10.4,
                    "display_aspect_ratio": 10.4,
                    "pixel_aspect_ratio": 1.0
                },
                {
                    "name": "6656 x 1664 | RED 6.5K 4:1 Ana 1.3x",
                    "width": 6656,
                    "height": 1664,
                    "storage_aspect_ratio": 5.2,
                    "display_aspect_ratio": 5.2,
                    "pixel_aspect_ratio": 1.0
                },
                {
                    "name": "6656 x 2808 | RED 6.5K 2.37 WS Ana 1.3x",
                    "width": 6656,
                    "height": 2808,
                    "storage_aspect_ratio": 3.081481,
                    "display_aspect_ratio": 3.081481,
                    "pixel_aspect_ratio": 1.0
                },
                {
                    "name": "6656 x 3328 | RED 6.5K 2:1 Ana 1.3x",
                    "width": 6656,
                    "height": 3328,
                    "storage_aspect_ratio": 2.6,
                    "display_aspect_ratio": 2.6,
                    "pixel_aspect_ratio": 1.0
                },
                {
                    "name": "6656 x 3536 | RED 6.5K Full Ana 1.3x",
                    "width": 6656,
                    "height": 3536,
                    "storage_aspect_ratio": 2.447055,
                    "display_aspect_ratio": 2.447055,
                    "pixel_aspect_ratio": 1.0
                },
                {
                    "name": "6144 x 3456 | RED 6.5K 16:9 Ana 2.0x",
                    "width": 6144,
                    "height": 3456,
                    "storage_aspect_ratio": 3.55554,
                    "display_aspect_ratio": 3.55554,
                    "pixel_aspect_ratio": 1.0
                },
                {
                    "name": "6656 x 832 | RED 6.5K 8:1 Ana 2.0x",
                    "width": 6656,
                    "height": 832,
                    "storage_aspect_ratio": 16,
                    "display_aspect_ratio": 16,
                    "pixel_aspect_ratio": 1.0
                },
                {
                    "name": "6656 x 1664 | RED 6.5K 4:1 Ana 2.0x",
                    "width": 6656,
                    "height": 1664,
                    "storage_aspect_ratio": 8,
                    "display_aspect_ratio": 8,
                    "pixel_aspect_ratio": 1.0
                },
                {
                    "name": "6656 x 2808 | RED 6.5K 2.37 WS Ana 2.0x",
                    "width": 6656,
                    "height": 2808,
                    "storage_aspect_ratio": 4.74074,
                    "display_aspect_ratio": 4.74074,
                    "pixel_aspect_ratio": 1.0
                },
                {
                    "name": "6656 x 3328 | RED 6.5K 2:1 Ana 2.0x",
                    "width": 6656,
                    "height": 3328,
                    "storage_aspect_ratio": 4,
                    "display_aspect_ratio": 4,
                    "pixel_aspect_ratio": 1.0
                },
                {
                    "name": "6656 x 3536 | RED 6.5K Full Ana 2.0x",
                    "width": 6656,
                    "height": 3536,
                    "storage_aspect_ratio": 3.7647,
                    "display_aspect_ratio": 3.7647,
                    "pixel_aspect_ratio": 1.0
                }
            ]
        }
    ]
}
