{
    "SearchSettings": {
        "Tools": [
            {
                "Name": "2D Transform",
                "Tags": [
                    "Camera Shake",
                    "Stabilizer",
                    "Pan",
                    "Scan"
                ]
            },
            {
                "Name": "Action",
                "Weight": 10,
                "Tags": [
                    "3D",
                    "Comp",
                    "FBX",
                    "Alembic",
                    "Geometry",
                    "SVG",
                    "Camera",
                    "Lighting",
                    "Particles",
                    "Lens Flare",
                    "Texture",
                    "Maps",
                    "Deform",
                    "Tracking"
                ]
            },
            {
                "Name": "Blur",
                "Weight": 10,
                "Tags": [
                    "Gaussian",
                    "Radial"
                ]
            },
            {
                "Name": "Colour Blend",
                "Tags": [
                    "Color"
                ]
            },
            {
                "Name": "Colour Correct",
                "Tags": [
                    "Color"
                ]
            },
            {
                "Name": "Colour Curves",
                "Tags": [
                    "Color"
                ]
            },
            {
                "Name": "Colour Source",
                "Tags": [
                    "Color",
                    "Bars",
                    "Noise",
                    "Gradient"
                ]
            },
            {
                "Name": "Colour Warper",
                "Tags": [
                    "Color"
                ]
            },
            {
                "Name": "Colour Mgmt",
                "Tags": [
                    "Color",
                    "Management",
                    "Lut"
                ]
            },
            {
                "Name": "Compass",
                "Tags": [
                    "Backdrop"
                ]
            },
            {
                "Name": "Image",
                "Weight": 10,
                "Tags": [
                    "MasterGrade",
                    "Colour",
                    "Color",
                    "Grading",
                    "Selective",
                    "Secondary",
                    "Semantic",
                    "Look"
                ]
            },
            {
                "Name": "Look",
                "Tags": [
                    "CDL"
                ]
            },
            {
                "Name": "MasterK",
                "Weight": 10,
                "Tags": [
                    "Keyer"
                ]
            },
            {
                "Name": "Matchbox",
                "Tags": [
                    "Plugins"
                ]
            },
            {
                "Name": "Mono",
                "Weight": 10
            },
            {
                "Name": "Motif",
                "Tags": [
                    "Kaleidoscope"
                ]
            },
            {
                "Name": "MUX",
                "Tags": [
                    "Switch"
                ]
            },
            {
                "Name": "OpenFX",
                "Tags": [
                    "Plugins",
                    "OFX"
                ]
            },
            {
                "Name": "Pixel Spread",
                "Tags": [
                    "Edge"
                ]
            },
            {
                "Name": "Recursive Ops",
                "Tags": [
                    "Clean",
                    "Plate"
                ]
            },
            {
                "Name": "Render",
                "Weight": 10
            },
            {
                "Name": "Resize & Crop",
                "Tags": [
                    "Pan",
                    "Scan",
                    "Resolution"
                ]
            },
            {
                "Name": "Sparks",
                "Tags": [
                    "Plugins"
                ]
            },
            {
                "Name": "Substance Noise",
                "Tags": [
                    "Pattern",
                    "Generators"
                ]
            },
            {
                "Name": "Substance Splatter",
                "Tags": [
                    "Pattern"
                ]
            },
            {
                "Name": "Text",
                "Tags": [
                    "Title"
                ]
            },
            {
                "Name": "Timewarp",
                "Tags": [
                    "Speed",
                    "Ramp"
                ]
            },
            {
                "Name": "Write File",
                "Tags": [
                    "Export"
                ]
            },
            {
                "Name": "MasterGrade",
                "Type": "Matchbox",
                "Weight": 28,
                "Tags": [
                    "Colour",
                    "Color",
                    "Curves",
                    "Lift",
                    "Gamma",
                    "Gain",
                    "Primary",
                    "Tone",
                    "Correct"
                ]
            },
            {
                "Name": "PhysicalDefocus",
                "Type": "Matchbox",
                "Weight": 10,
                "Tags": [
                    "Bokeh",
                    "Depth"
                ]
            },
            {
                "Name": "A2Beauty",
                "Type": "Matchbox",
                "Weight": 22,
                "Tags": [
                    "Frequency",
                    "Dodge",
                    "Burn"
                ]
            },
            {
                "Name": "ColourMgmt",
                "Type": "Matchbox",
                "Tags": [
                    "Color",
                    "Management",
                    "Lut"
                ]
            },
            {
                "Name": "Axis",
                "Weight": 2,
                "Tags": [
                    "Position",
                    "Tracking"
                ]
            },
            {
                "Name": "Camera Analysis",
                "Weight": 10,
                "Tags": [
                    "Tracking",
                    "Analyzer",
                    "Mono"
                ]
            },
            {
                "Name": "Diffuse Map",
                "Tags": [
                    "Texture"
                ]
            },
            {
                "Name": "GMask",
                "Tags": [
                    "Window"
                ]
            },
            {
                "Name": "GMask Ellipse",
                "Tags": [
                    "Window",
                    "Vignette"
                ]
            },
            {
                "Name": "GMask Rectangle",
                "Tags": [
                    "Window"
                ]
            },
            {
                "Name": "Lightbox",
                "Tags": [
                    "Plugins"
                ]
            },
            {
                "Name": "Material",
                "Tags": [
                    "Refraction",
                    "Light Wrap"
                ]
            },
            {
                "Name": "Perspective Grid",
                "Tags": [
                    "Tracking"
                ]
            },
            {
                "Name": "Replica",
                "Tags": [
                    "Instance"
                ]
            },
            {
                "Name": "Selective",
                "Tags": [
                    "Secondary",
                    "Keyer",
                    "Semantic",
                    "Matte"
                ]
            },
            {
                "Name": "Shader",
                "Tags": [
                    "PBR"
                ]
            },
            {
                "Name": "Surface",
                "Tags": [
                    "Blending",
                    "Resolution",
                    "Tracking",
                    "Lens"
                ]
            },
            {
                "Name": "2D Transform",
                "Type": "Timeline FX",
                "Tags": [
                    "Camera Shake",
                    "Stabilizer",
                    "Pan",
                    "Scan"
                ]
            },
            {
                "Name": "Action",
                "Type": "Timeline FX",
                "Weight": 10,
                "Tags": [
                    "3D",
                    "Comp",
                    "FBX",
                    "Alembic",
                    "Geometry",
                    "SVG",
                    "Camera",
                    "Lighting",
                    "Particles",
                    "Lens Flare",
                    "Texture",
                    "Maps",
                    "Deform",
                    "Tracking"
                ]
            },
            {
                "Name": "Blur",
                "Type": "Timeline FX",
                "Tags": [
                    "Gaussian",
                    "Radial"
                ]
            },
            {
                "Name": "Colour Correct",
                "Type": "Timeline FX",
                "Tags": [
                    "Color"
                ]
            },
            {
                "Name": "Colour Warper",
                "Type": "Timeline FX",
                "Tags": [
                    "Color"
                ]
            },
            {
                "Name": "Colour Mgmnt",
                "Type": "Timeline FX",
                "Tags": [
                    "Color",
                    "Management",
                    "Lut"
                ]
            },
            {
                "Name": "Image",
                "Type": "Timeline FX",
                "Weight": 10,
                "Tags": [
                    "MasterGrade",
                    "Colour",
                    "Color",
                    "Grading",
                    "Selective",
                    "Secondary",
                    "Semantic",
                    "Look"
                ]
            },
            {
                "Name": "Look",
                "Type": "Timeline FX",
                "Tags": [
                    "CDL"
                ]
            },
            {
                "Name": "Matchbox",
                "Type": "Timeline FX",
                "Tags": [
                    "Plugins"
                ]
            },
            {
                "Name": "OpenFX",
                "Type": "Timeline FX",
                "Tags": [
                    "Plugins",
                    "OFX"
                ]
            },
            {
                "Name": "Resize",
                "Type": "Timeline FX",
                "Tags": [
                    "Pan",
                    "Scan",
                    "Resolution"
                ]
            },
            {
                "Name": "Sparks",
                "Type": "Timeline FX",
                "Tags": [
                    "Plugins"
                ]
            },
            {
                "Name": "MasterGrade",
                "Type": "Timeline FX Matchbox",
                "Weight": 10,
                "Tags": [
                    "Colour",
                    "Color",
                    "Curves",
                    "Lift",
                    "Gamma",
                    "Gain",
                    "Primary",
                    "Tone",
                    "Correct"
                ]
            },
            {
                "Name": "PhysicalDefocus",
                "Type": "Timeline FX Matchbox",
                "Weight": 10,
                "Tags": [
                    "Bokeh",
                    "Depth"
                ]
            },
            {
                "Name": "A2Beauty",
                "Type": "Timeline FX Matchbox",
                "Weight": 10,
                "Tags": [
                    "Frequency",
                    "Dodge",
                    "Burn"
                ]
            },
            {
                "Name": "Add Adjustment Segment",
                "Type": "Batch FX",
                "Tags": [
                    "Batch FX",
                    "BFX"
                ]
            },
            {
                "Name": "Batch FX",
                "Type": "Batch FX",
                "Tags": [
                    "Batch FX",
                    "BFX"
                ]
            },
            {
                "Name": "Selection As 3D Comp",
                "Type": "Batch FX",
                "Tags": [
                    "Batch FX",
                    "BFX"
                ]
            },
            {
                "Name": "Selection As Clip",
                "Type": "Batch FX",
                "Tags": [
                    "Batch FX",
                    "BFX"
                ]
            },
            {
                "Name": "Selection As Flowgraph",
                "Type": "Batch FX",
                "Tags": [
                    "Batch FX",
                    "BFX"
                ]
            },
            {
                "Name": "MLHumanFaceExtraction",
                "Type": "Matchbox",
                "Weight": 1
            },
            {
                "Name": "Normal Map",
                "Weight": 1
            },
            {
                "Name": "Matte Edge",
                "Weight": 1
            },
            {
                "Name": "Comp",
                "Weight": 1
            },
            {
                "Name": "Blur",
                "Type": "Matchbox",
                "Weight": 1
            },
            {
                "Name": "DropShadow",
                "Type": "Matchbox",
                "Weight": 2
            },
            {
                "Name": "S_Invert",
                "Type": "Timeline FX OpenFX",
                "Weight": 1
            },
            {
                "Name": "Sharpen",
                "Type": "Matchbox",
                "Weight": 2
            },
            {
                "Name": "FrontMatteOffset",
                "Type": "Matchbox",
                "Weight": 2
            },
            {
                "Name": "Negative",
                "Weight": 1
            },
            {
                "Name": "MLSkyExtraction",
                "Type": "Matchbox",
                "Weight": 1
            },
            {
                "Name": "GMask Tracer",
                "Weight": 4
            }
        ],
        "Learn": []
    }
}