{
    "Settings": [
        {
            "name": "PPFxAutoKey",
            "value": true
        },
        {
            "name": "PPFxTimeLineRangeMode",
            "value": 1
        },
        {
            "name": "PPFxTimeLineVMMode",
            "value": 0
        },
        {
            "name": "PPFxTimeLineVMLeftOffset",
            "value": 0
        },
        {
            "name": "PPFxTimeLineVMRightOffset",
            "value": 0
        },
        {
            "name": "PPFxTimeLineCacheOnPlayback",
            "value": false
        }
    ]
}